{"cityZones":[{"id":"COMMERCIAL","label":{"DE":"Kommerziell","EN":"Commercial","ES":"Comercial","FR":"Commercial","IT":"Commerciale","PT":"Comercial"},"value":7,"color":4814040,"miniMapColor":4814040,"includedCityZoneIds":["SERVICE"]},{"id":"CIVICS","label":{"DE":"Städtischer","EN":"Civic","ES":"Cívico","FR":"Civique","IT":"Civico","PT":"Cívico"},"value":8,"color":16777215,"miniMapColor":1973790,"includedCityZoneIds":[]},{"id":"HC_RESIDENTIAL","label":{"DE":"Hochwertige Immobilien","EN":"High-class Residential","ES":"Clase Alta Residencial","FR":"Résidentiel Haut de Gamme","IT":"Residenziale di Alta Classe","PT":"Residencial de Alta Classe"},"value":3,"color":12648379,"miniMapColor":12648379,"includedCityZoneIds":[]},{"id":"INDUSTRIAL","label":{"DE":"Industriell","EN":"Industrial","ES":"Industrial","FR":"Industriel","IT":"Industriale","PT":"Industrial"},"value":6,"color":14145928,"miniMapColor":14145928,"includedCityZoneIds":["WAREHOUSE"]},{"id":"LC_RESIDENTIAL","label":{"DE":"Preiswerte Immobilien","EN":"Low-class Residential","ES":"Residencial de Clase Baja","FR":"Résidentiel Bas de Gamme","IT":"Residenziale di Classe Bassa","PT":"Residencial de Baixa Classe"},"value":5,"color":2312222,"miniMapColor":2312222,"includedCityZoneIds":[]},{"id":"MC_RESIDENTIAL","label":{"DE":"Bürgerliche Immobilien","EN":"Middle-class Residential","ES":"Clase Media Residencial","FR":"Classe Moyenne Résidentiel","IT":"Residenziale di Classe Media","PT":"Residencial de Classe Média"},"value":4,"color":5219139,"miniMapColor":5219139,"includedCityZoneIds":[]},{"id":"MAUSOLEUM","label":{"DE":"Mausoluem","EN":"Mausoluem","ES":"Mausoluem","FR":"Mausoluem","IT":"Mausoluem","PT":"Mausoluem"},"value":12,"color":16777215,"miniMapColor":16777215,"includedCityZoneIds":[]},{"id":"OFFICES","label":{"DE":"Büros","EN":"Offices","ES":"Oficinas","FR":"Des Bureaux","IT":"Uffici","PT":"Escritórios"},"value":9,"color":3753096,"miniMapColor":3753096,"includedCityZoneIds":[]},{"id":"RESERVED","label":{"DE":"Reserviert","EN":"Reserved","ES":"Reservado","FR":"Réservé","IT":"Riservato","PT":"Reservado"},"value":1,"color":8388608,"miniMapColor":8388608,"includedCityZoneIds":[]},{"id":"RESIDENTIAL","label":{"DE":"Wohn","EN":"Restaurant","ES":"Residencial","FR":"Résidentiel","IT":"Residenziale","PT":"Residencial"},"value":2,"color":32896,"miniMapColor":32896,"includedCityZoneIds":["HC_RESIDENTIAL","LC_RESIDENTIAL","MC_RESIDENTIAL"]},{"id":"SERVICE","label":{"DE":"Dienstleistungen","EN":"Service","ES":"Servicio","FR":"Service","IT":"Servizio","PT":"Serviço"},"value":10,"color":4814040,"miniMapColor":4814040,"includedCityZoneIds":[]},{"id":"WAREHOUSE","label":{"DE":"Warenhaus","EN":"Warehouse","ES":"Almacén","FR":"Entrepôt","IT":"Magazzino","PT":"Armazém"},"value":11,"color":14145928,"miniMapColor":14145928,"includedCityZoneIds":[]}],"industryCategories":[{"id":"NONE","label":{"DE":"Keine","EN":"None","ES":"Ninguna","FR":"Aucun","IT":"Nessuna","PT":"Nenhum"}},{"id":"CIVIC","label":{"DE":"Städtischer","EN":"Civic","ES":"Cívico","FR":"Civique","IT":"Civico","PT":"Cívico"}},{"id":"COMMERCE","label":{"DE":"Handel","EN":"Commerce","ES":"Comercio","FR":"Commerce","IT":"Commercio","PT":"Comércio"}},{"id":"INDUSTRY","label":{"DE":"Industriegebäude","EN":"Industry","ES":"Industria","FR":"Industrie","IT":"Industria","PT":"Indústria"}},{"id":"LOGISTICS","label":{"DE":"Logistik","EN":"Logistics","ES":"Logística","FR":"Logistique","IT":"Logistica","PT":"Logística"}},{"id":"REAL_ESTATE","label":{"DE":"Immobilien","EN":"Real Estate","ES":"Bienes Raíces","FR":"Immobilier","IT":"Immobiliare","PT":"Imobiliária"}},{"id":"SERVICE","label":{"DE":"Dienstleistungen","EN":"Service","ES":"Servicio","FR":"Service","IT":"Servizio","PT":"Serviço"}}],"industryTypes":[{"id":"APPLIANCE","label":{"DE":"Haushaltsgeräte","EN":"Appliances","ES":"Accesorios","FR":"Appareils Électroménagers","IT":"Appliances","PT":"Eletrodomésticos"}},{"id":"AUTOMOBILE","label":{"DE":"Kraftfahrzeug","EN":"Automobile","ES":"Automóvil","FR":"Voiture","IT":"Automobile","PT":"Automóvel"}},{"id":"BANKING","label":{"DE":"Bank","EN":"Banking","ES":"Bancario","FR":"Bancaire","IT":"Bancario","PT":"Bancário"}},{"id":"BAR","label":{"DE":"Lokal","EN":"Bars","ES":"Barras","FR":"Les Bars","IT":"Barre","PT":"Barras"}},{"id":"BOOK","label":{"DE":"Bücher","EN":"Book","ES":"Libro","FR":"Livre","IT":"Libro","PT":"Livro"}},{"id":"CHEMICAL","label":{"DE":"Chemikalien","EN":"Chemical","ES":"Químico","FR":"Chimique","IT":"Chimico","PT":"Químico"}},{"id":"CLOTHES","label":{"DE":"Kleiderfabrik","EN":"Clothing","ES":"Ropa","FR":"Vêtements","IT":"Capi di Abbigliamento","PT":"Roupas"}},{"id":"COAL","label":{"DE":"Kohle","EN":"Coal","ES":"Carbón","FR":"Charbon","IT":"Carbone","PT":"Carvão"}},{"id":"COLLEGE","label":{"DE":"Universität","EN":"College","ES":"Universidad","FR":"Université","IT":"Università","PT":"Faculdade"}},{"id":"COMPACT_DISC","label":{"DE":"CD","EN":"Compact Disc","ES":"Disco Compacto","FR":"Disque Compact","IT":"Compact Disc","PT":"Disco Compacto"}},{"id":"COMPUTER","label":{"DE":"Computer","EN":"Computer","ES":"Computadora","FR":"Ordinateur","IT":"Computer","PT":"Computador"}},{"id":"COMPUTER_SERVICES","label":{"DE":"Computer Dienstleistungen","EN":"Computer Services","ES":"Servicios Informaticos","FR":"Services Informatiques","IT":"Servizi Informatici","PT":"Serviços Informáticos"}},{"id":"CONSTRUCTION","label":{"DE":"Bauindustrie","EN":"Construction","ES":"Construcción","FR":"Construction","IT":"Costruzione","PT":"Construção"}},{"id":"CRUDE_OIL","label":{"DE":"Rohöl","EN":"Crude Oil","ES":"Petróleo Crudo","FR":"Huile Brute","IT":"Olio Crudo","PT":"Óleo Cru"}},{"id":"ELECTRONIC_COMPONENT","label":{"DE":"Elektronikbauteile","EN":"Electronic Component","ES":"Componente Electrónico","FR":"Composant Élèctronique","IT":"Componente Elettronico","PT":"Componente Eletronico"}},{"id":"FABRIC","label":{"DE":"Gewebekonstruktion","EN":"Fabric","ES":"Tela","FR":"En Tissu","IT":"Tessuto","PT":"Tecido"}},{"id":"FAST_FOOD","label":{"DE":"Schnellrestaurant","EN":"Fast Food","ES":"Comida Rápida","FR":"Fast Food","IT":"Fast Food","PT":"Comida Rápida"}},{"id":"FARMING","label":{"DE":"Landwirtschaft","EN":"Farming","ES":"Agricultura","FR":"Agriculture","IT":"Agricoltura","PT":"Agricultura"}},{"id":"FIRE","label":{"DE":"Brandschutz","EN":"Fire Safety","ES":"Seguridad Contra Incendios","FR":"La Sécurité Incendie","IT":"Sicurezza Antincendio","PT":"Segurança Contra Incêndios"}},{"id":"FOOD","label":{"DE":"Essen","EN":"Food","ES":"Comida","FR":"Aliments","IT":"Cibo","PT":"Comida"}},{"id":"FUNERAL_SERVICES","label":{"DE":"Bestattungsinstitut","EN":"Funeral Services","ES":"Servicios Fúnebres","FR":"Services Funéraires","IT":"Servizi Funebri","PT":"Serviços Funerários"}},{"id":"FURNITURE","label":{"DE":"Möbelindustrie","EN":"Furniture","ES":"Mueble","FR":"Meubles","IT":"Mobilia","PT":"Mobília"}},{"id":"GARBAGE","label":{"DE":"Müll","EN":"Garbage","ES":"Basura","FR":"Des Ordures","IT":"Spazzatura","PT":"Lixo"}},{"id":"GASOLINE","label":{"DE":"Treibstoff","EN":"Gasoline","ES":"Gasolina","FR":"De L'Essence","IT":"Gasolio","PT":"Gasolina"}},{"id":"GENERAL","label":{"DE":"Allgemein","EN":"General","ES":"General","FR":"Général","IT":"Generale","PT":"Geral"}},{"id":"GOVERNMENT","label":{"DE":"Regierung","EN":"Government","ES":"Gobierno","FR":"Gouvernement","IT":"Governo","PT":"Governo"}},{"id":"HC_RESIDENTIAL","label":{"DE":"Hochwertige Immobilien","EN":"High-class Residential","ES":"Clase Alta Residencial","FR":"Résidentiel Haut de Gamme","IT":"Residenziale di Alta Classe","PT":"Residencial de Alta Classe"}},{"id":"HEADQUARTERS","label":{"DE":"Zentrale","EN":"Headquarters","ES":"Sede","FR":"Quartier Général","IT":"Quartier Generale","PT":"Quartel General"}},{"id":"HOSPITAL","label":{"DE":"Krankenhaus","EN":"Hospital","ES":"Hospital","FR":"Hôpital","IT":"Ospedale","PT":"Hospital"}},{"id":"LC_RESIDENTIAL","label":{"DE":"Preiswerte Immobilien","EN":"Low-class Residential","ES":"Residencial de Clase Baja","FR":"Résidentiel Bas de Gamme","IT":"Residenziale di Classe Bassa","PT":"Residencial de Baixa Classe"}},{"id":"LEGAL_SERVICES","label":{"DE":"Rechtsdienstleistungen","EN":"Legal Services","ES":"Servicios Jurídicos","FR":"Services Juridiques","IT":"Servizi Legali","PT":"Serviços Legais"}},{"id":"LIQUOR","label":{"DE":"Spirituosen","EN":"Liquor","ES":"Espíritu","FR":"Alcool","IT":"Liquore","PT":"Licor"}},{"id":"MACHINERY","label":{"DE":"Maschinen","EN":"Machinery","ES":"Maquinaria","FR":"Machinerie","IT":"Macchinario","PT":"Maquinário"}},{"id":"MARKET","label":{"DE":"Markt","EN":"Market","ES":"Mercado","FR":"Marché","IT":"Mercato","PT":"Mercado"}},{"id":"MAUSOLEUM","label":{"DE":"Mausoleum","EN":"Mausoleum","ES":"Mausoleo","FR":"Mausolée","IT":"Mausoleo","PT":"Mausoléu"}},{"id":"MC_RESIDENTIAL","label":{"DE":"Bürgerliche Immobilien","EN":"Middle-class Residential","ES":"Clase Media Residencial","FR":"Classe Moyenne Résidentiel","IT":"Residenziale di Classe Media","PT":"Residencial de Classe Média"}},{"id":"METAL","label":{"DE":"Metalurgie","EN":"Metallurgy","ES":"Metalurgia","FR":"Métallurgie","IT":"Metallurgia","PT":"Metalurgia"}},{"id":"MOVIE","label":{"DE":"Kino","EN":"Movie","ES":"Película","FR":"Film","IT":"Film","PT":"Filme"}},{"id":"MUSEUM","label":{"DE":"Museum","EN":"Museum","ES":"Museo","FR":"Musée","IT":"Museo","PT":"Museu"}},{"id":"OFFICE","label":{"DE":"Büro","EN":"Office","ES":"Oficina","FR":"Bureau","IT":"Ufficio","PT":"Escritório"}},{"id":"ORE","label":{"DE":"Erz","EN":"Ore","ES":"Mineral","FR":"Minerai","IT":"Minerale","PT":"Minério"}},{"id":"PAPER","label":{"DE":"Papier","EN":"Paper","ES":"Papel","FR":"Papier","IT":"Carta","PT":"Papel"}},{"id":"PARK","label":{"DE":"Park","EN":"Park","ES":"Parque","FR":"Parc","IT":"Parco","PT":"Parque"}},{"id":"PHARMACEUTICAL","label":{"DE":"Arzneimittel","EN":"Pharmaceutical","ES":"Farmacéutico","FR":"Pharmaceutique","IT":"Farmaceutico","PT":"Farmacêutico"}},{"id":"PLASTIC","label":{"DE":"Kunststoff","EN":"Plastic","ES":"Plastico","FR":"Plastique","IT":"Plastica","PT":"Plástico"}},{"id":"POLICE","label":{"DE":"Polizei","EN":"Police","ES":"Policía","FR":"Police","IT":"Polizia","PT":"Polícia"}},{"id":"PRISON","label":{"DE":"Haftanstalt","EN":"Prison","ES":"Prisión","FR":"Prison","IT":"Prigione","PT":"Prisão"}},{"id":"PROCESSED_FOOD","label":{"DE":"Verarbeitete Lebensmittel","EN":"Processed Food","ES":"Alimentos Procesados","FR":"Aliments Transformés","IT":"Cibo Trattato","PT":"Comida Processada"}},{"id":"RAW_CHEMICAL","label":{"DE":"Rohchemikalien","EN":"Raw Chemical","ES":"Química Cruda","FR":"Produit Chimique Brut","IT":"Prodotto Chimico Crudo","PT":"Químico Bruto"}},{"id":"RESIDENTIAL","label":{"DE":"Wohn","EN":"Residential","ES":"Residencial","FR":"Résidentiel","IT":"Residenziale","PT":"Residencial"}},{"id":"RESTAURANT","label":{"DE":"Restaurant","EN":"Restaurant","ES":"Restaurante","FR":"Restaurant","IT":"Ristorante","PT":"Restaurante"}},{"id":"SCHOOL","label":{"DE":"Schule","EN":"School","ES":"Colegio","FR":"École","IT":"Scuola","PT":"Escola"}},{"id":"SILICON","label":{"DE":"Silizium","EN":"Silicon","ES":"Silicio","FR":"Silicium","IT":"Silicio","PT":"Silício"}},{"id":"STONE","label":{"DE":"Stein","EN":"Stone","ES":"Piedra","FR":"Pierre","IT":"Pietra","PT":"Pedra"}},{"id":"TELEVISION","label":{"DE":"Fernsehen","EN":"Television","ES":"Televisión","FR":"Télévision","IT":"Televisione","PT":"Televisão"}},{"id":"TIMBER","label":{"DE":"Holz","EN":"Timber","ES":"Madera","FR":"Bois","IT":"Legname","PT":"Madeira"}},{"id":"TOY","label":{"DE":"Spielzeug","EN":"Toy","ES":"Juguete","FR":"Jouet","IT":"Giocattolo","PT":"Brinquedo"}},{"id":"WAREHOUSE","label":{"DE":"Lagerhalle","EN":"Warehouse","ES":"Almacén","FR":"Entrepôt","IT":"Magazzino","PT":"Armazém"}}],"levels":[{"id":"APPRENTICE","label":{"DE":"Lehrling","EN":"Apprentice","ES":"Aprendiz","FR":"Apprenti","IT":"Novizio","PT":"Aprendiz"},"description":{"DE":"Die Wirtschaft lernen.","EN":"Learning the economy.","ES":"Aprender la economía.","FR":"Apprendre l'économie.","IT":"Imparare l'economia.","PT":"Aprendendo a economia."},"level":1,"facilityLimit":50,"supplierPriority":true,"supplierIfel":true,"rewardPrestige":25,"refundResearch":0.5,"refundDemolition":1,"requiredFee":0,"requiredHourlyProfit":0,"requiredPrestige":0},{"id":"ENTREPRENEUR","label":{"DE":"Unternehmer","EN":"Entrepreneur","ES":"Empresario","FR":"Entrepreneur","IT":"Imprenditore","PT":"Empreendedor"},"description":{"DE":"Entwicklung einer Strategie.","EN":"Developing a strategy.","ES":"Desarrollar una estrategia.","FR":"Développer une stratégie.","IT":"Sviluppare una strategia.","PT":"Desenvolvendo uma estratégia."},"level":2,"facilityLimit":150,"supplierPriority":true,"supplierIfel":true,"rewardPrestige":50,"refundResearch":0.33,"refundDemolition":0.66,"requiredFee":100000000,"requiredHourlyProfit":1000,"requiredPrestige":0},{"id":"TYCOON","label":{"DE":"Magnat","EN":"Tycoon","ES":"Magnate","FR":"Investisseur","IT":"Magnate","PT":"Magnata"},"description":{"DE":"Zugang zu Tier 2 -Technologien haben.","EN":"Have access to Tier 2 technologies.","ES":"Tener acceso a tecnologías de nivel 2.","FR":"Avoir accès aux technologies de niveau 2.","IT":"Avere accesso alle tecnologie di livello 2.","PT":"Tenha acesso às tecnologias de Nível 2."},"level":3,"facilityLimit":400,"supplierPriority":false,"supplierIfel":false,"rewardPrestige":100,"refundResearch":0,"refundDemolition":0,"requiredFee":500000000,"requiredHourlyProfit":5000,"requiredPrestige":0},{"id":"MASTER","label":{"DE":"Meister","EN":"Master","ES":"Master","FR":"Maître","IT":"Master","PT":"Mestre"},"description":{"DE":"Zugang zu Tier 3 -Technologien haben.","EN":"Have access to Tier 3 technologies.","ES":"Tener acceso a tecnologías de nivel 3.","FR":"Avoir accès aux technologies de niveau 3.","IT":"Avere accesso alle tecnologie di livello 3.","PT":"Tenha acesso às tecnologias de Nível 3."},"level":4,"facilityLimit":800,"supplierPriority":false,"supplierIfel":false,"rewardPrestige":200,"refundResearch":0,"refundDemolition":0,"requiredFee":2000000000,"requiredHourlyProfit":50000,"requiredPrestige":2500},{"id":"PARADIGM","label":{"DE":"Vorbild","EN":"Paradigm","ES":"Paradigma","FR":"Patron","IT":"Paradigma","PT":"Paradigma"},"description":{"DE":"Zugang zu Tier 4 -Technologien haben.","EN":"Have access to Tier 4 technologies.","ES":"Tener acceso a tecnologías de nivel 4.","FR":"Avoir accès aux technologies de niveau 4.","IT":"Avere accesso alle tecnologie di livello 4.","PT":"Tenha acesso às tecnologias de Nível 4."},"level":5,"facilityLimit":1000,"supplierPriority":false,"supplierIfel":false,"rewardPrestige":400,"refundResearch":0,"refundDemolition":0,"requiredFee":20000000000,"requiredHourlyProfit":100000,"requiredPrestige":5000},{"id":"LEGEND","label":{"DE":"Legende","EN":"Legend","ES":"Leyenda","FR":"Légende","IT":"Leggenda","PT":"Lenda"},"description":{"DE":"Zugang zu Tier 5 -Technologien haben.","EN":"Have access to Tier 5 technologies.","ES":"Tener acceso a tecnologías de nivel 5.","FR":"Avoir accès aux technologies de niveau 5.","IT":"Avere accesso alle tecnologie di livello 5.","PT":"Tenha acesso às tecnologias de Nível 5."},"level":6,"facilityLimit":1500,"supplierPriority":false,"supplierIfel":false,"rewardPrestige":800,"refundResearch":0,"refundDemolition":0,"requiredFee":40000000000,"requiredHourlyProfit":500000,"requiredPrestige":15000}],"rankingTypes":[{"id":"corporation","type":"CORPORATION","unit":"COUNT","label":{"DE":"Gesellschaft","EN":"Corporation","ES":"Corporación","FR":"Entreprise","IT":"Società","PT":"Corporação"}},{"id":"profit","type":"FOLDER","label":{"DE":"Profit","EN":"Profit","ES":"Lucro","FR":"Profit","IT":"Profitto","PT":"Lucro"}},{"id":"prestige","type":"PRESTIGE","label":{"DE":"Prestige","EN":"Prestige","ES":"Prestigio","FR":"Prestige","IT":"Prestigio","PT":"Prestígio"},"unit":"COUNT"},{"id":"wealth","type":"WEALTH","unit":"CURRENCY","label":{"DE":"Reichtum","EN":"Wealth","ES":"Riqueza","FR":"Richesse","IT":"Ricchezza","PT":"Riqueza"}},{"id":"profit-total","parentId":"profit","type":"PROFIT","categoryTotal":true,"unit":"CURRENCY","industryCategoryId":null,"industryTypeId":null},{"id":"profit-INDUSTRY-APPLIANCE","parentId":"profit-INDUSTRY","type":"PROFIT","categoryTotal":false,"unit":"CURRENCY","industryCategoryId":"INDUSTRY","industryTypeId":"APPLIANCE"},{"id":"profit-INDUSTRY-AUTOMOBILE","parentId":"profit-INDUSTRY","type":"PROFIT","categoryTotal":false,"unit":"CURRENCY","industryCategoryId":"INDUSTRY","industryTypeId":"AUTOMOBILE"},{"id":"profit-INDUSTRY-CHEMICAL","parentId":"profit-INDUSTRY","type":"PROFIT","categoryTotal":false,"unit":"CURRENCY","industryCategoryId":"INDUSTRY","industryTypeId":"CHEMICAL"},{"id":"profit-INDUSTRY-CLOTHES","parentId":"profit-INDUSTRY","type":"PROFIT","categoryTotal":false,"unit":"CURRENCY","industryCategoryId":"INDUSTRY","industryTypeId":"CLOTHES"},{"id":"profit-INDUSTRY-COAL","parentId":"profit-INDUSTRY","type":"PROFIT","categoryTotal":false,"unit":"CURRENCY","industryCategoryId":"INDUSTRY","industryTypeId":"COAL"},{"id":"profit-INDUSTRY-COMPUTER","parentId":"profit-INDUSTRY","type":"PROFIT","categoryTotal":false,"unit":"CURRENCY","industryCategoryId":"INDUSTRY","industryTypeId":"COMPUTER"},{"id":"profit-INDUSTRY-CONSTRUCTION","parentId":"profit-INDUSTRY","type":"PROFIT","categoryTotal":false,"unit":"CURRENCY","industryCategoryId":"INDUSTRY","industryTypeId":"CONSTRUCTION"},{"id":"profit-INDUSTRY-ELECTRONIC_COMPONENT","parentId":"profit-INDUSTRY","type":"PROFIT","categoryTotal":false,"unit":"CURRENCY","industryCategoryId":"INDUSTRY","industryTypeId":"ELECTRONIC_COMPONENT"},{"id":"profit-INDUSTRY-FABRIC","parentId":"profit-INDUSTRY","type":"PROFIT","categoryTotal":false,"unit":"CURRENCY","industryCategoryId":"INDUSTRY","industryTypeId":"FABRIC"},{"id":"profit-INDUSTRY-FARMING","parentId":"profit-INDUSTRY","type":"PROFIT","categoryTotal":false,"unit":"CURRENCY","industryCategoryId":"INDUSTRY","industryTypeId":"FARMING"},{"id":"profit-INDUSTRY-FURNITURE","parentId":"profit-INDUSTRY","type":"PROFIT","categoryTotal":false,"unit":"CURRENCY","industryCategoryId":"INDUSTRY","industryTypeId":"FURNITURE"},{"id":"profit-INDUSTRY-LIQUOR","parentId":"profit-INDUSTRY","type":"PROFIT","categoryTotal":false,"unit":"CURRENCY","industryCategoryId":"INDUSTRY","industryTypeId":"LIQUOR"},{"id":"profit-INDUSTRY-MACHINERY","parentId":"profit-INDUSTRY","type":"PROFIT","categoryTotal":false,"unit":"CURRENCY","industryCategoryId":"INDUSTRY","industryTypeId":"MACHINERY"},{"id":"profit-INDUSTRY-METAL","parentId":"profit-INDUSTRY","type":"PROFIT","categoryTotal":false,"unit":"CURRENCY","industryCategoryId":"INDUSTRY","industryTypeId":"METAL"},{"id":"profit-INDUSTRY-ORE","parentId":"profit-INDUSTRY","type":"PROFIT","categoryTotal":false,"unit":"CURRENCY","industryCategoryId":"INDUSTRY","industryTypeId":"ORE"},{"id":"profit-INDUSTRY-PROCESSED_FOOD","parentId":"profit-INDUSTRY","type":"PROFIT","categoryTotal":false,"unit":"CURRENCY","industryCategoryId":"INDUSTRY","industryTypeId":"PROCESSED_FOOD"},{"id":"profit-INDUSTRY-RAW_CHEMICAL","parentId":"profit-INDUSTRY","type":"PROFIT","categoryTotal":false,"unit":"CURRENCY","industryCategoryId":"INDUSTRY","industryTypeId":"RAW_CHEMICAL"},{"id":"profit-INDUSTRY-SILICON","parentId":"profit-INDUSTRY","type":"PROFIT","categoryTotal":false,"unit":"CURRENCY","industryCategoryId":"INDUSTRY","industryTypeId":"SILICON"},{"id":"profit-INDUSTRY-STONE","parentId":"profit-INDUSTRY","type":"PROFIT","categoryTotal":false,"unit":"CURRENCY","industryCategoryId":"INDUSTRY","industryTypeId":"STONE"},{"id":"profit-INDUSTRY-TIMBER","parentId":"profit-INDUSTRY","type":"PROFIT","categoryTotal":false,"unit":"CURRENCY","industryCategoryId":"INDUSTRY","industryTypeId":"TIMBER"},{"id":"profit-INDUSTRY-TOY","parentId":"profit-INDUSTRY","type":"PROFIT","categoryTotal":false,"unit":"CURRENCY","industryCategoryId":"INDUSTRY","industryTypeId":"TOY"},{"id":"profit-INDUSTRY-MOVIE","parentId":"profit-INDUSTRY","type":"PROFIT","categoryTotal":false,"unit":"CURRENCY","industryCategoryId":"INDUSTRY","industryTypeId":"MOVIE"},{"id":"profit-INDUSTRY-COMPACT_DISC","parentId":"profit-INDUSTRY","type":"PROFIT","categoryTotal":false,"unit":"CURRENCY","industryCategoryId":"INDUSTRY","industryTypeId":"COMPACT_DISC"},{"id":"profit-INDUSTRY-CRUDE_OIL","parentId":"profit-INDUSTRY","type":"PROFIT","categoryTotal":false,"unit":"CURRENCY","industryCategoryId":"INDUSTRY","industryTypeId":"CRUDE_OIL"},{"id":"profit-INDUSTRY-GASOLINE","parentId":"profit-INDUSTRY","type":"PROFIT","categoryTotal":false,"unit":"CURRENCY","industryCategoryId":"INDUSTRY","industryTypeId":"GASOLINE"},{"id":"profit-INDUSTRY-BOOK","parentId":"profit-INDUSTRY","type":"PROFIT","categoryTotal":false,"unit":"CURRENCY","industryCategoryId":"INDUSTRY","industryTypeId":"BOOK"},{"id":"profit-INDUSTRY-PAPER","parentId":"profit-INDUSTRY","type":"PROFIT","categoryTotal":false,"unit":"CURRENCY","industryCategoryId":"INDUSTRY","industryTypeId":"PAPER"},{"id":"profit-INDUSTRY-PHARMACEUTICAL","parentId":"profit-INDUSTRY","type":"PROFIT","categoryTotal":false,"unit":"CURRENCY","industryCategoryId":"INDUSTRY","industryTypeId":"PHARMACEUTICAL"},{"id":"profit-INDUSTRY","parentId":"profit","type":"FOLDER","categoryTotal":false,"industryCategoryId":"INDUSTRY","industryTypeId":null},{"id":"profit-INDUSTRY-total","parentId":"profit-INDUSTRY","type":"PROFIT","categoryTotal":true,"unit":"CURRENCY","industryCategoryId":"INDUSTRY","industryTypeId":null},{"id":"profit-COMMERCE-APPLIANCE","parentId":"profit-COMMERCE","type":"PROFIT","categoryTotal":false,"unit":"CURRENCY","industryCategoryId":"COMMERCE","industryTypeId":"APPLIANCE"},{"id":"profit-COMMERCE-AUTOMOBILE","parentId":"profit-COMMERCE","type":"PROFIT","categoryTotal":false,"unit":"CURRENCY","industryCategoryId":"COMMERCE","industryTypeId":"AUTOMOBILE"},{"id":"profit-COMMERCE-BAR","parentId":"profit-COMMERCE","type":"PROFIT","categoryTotal":false,"unit":"CURRENCY","industryCategoryId":"COMMERCE","industryTypeId":"BAR"},{"id":"profit-COMMERCE-BOOK","parentId":"profit-COMMERCE","type":"PROFIT","categoryTotal":false,"unit":"CURRENCY","industryCategoryId":"COMMERCE","industryTypeId":"BOOK"},{"id":"profit-COMMERCE-CLOTHES","parentId":"profit-COMMERCE","type":"PROFIT","categoryTotal":false,"unit":"CURRENCY","industryCategoryId":"COMMERCE","industryTypeId":"CLOTHES"},{"id":"profit-COMMERCE-FOOD","parentId":"profit-COMMERCE","type":"PROFIT","categoryTotal":false,"unit":"CURRENCY","industryCategoryId":"COMMERCE","industryTypeId":"FOOD"},{"id":"profit-COMMERCE-FUNERAL_SERVICES","parentId":"profit-COMMERCE","type":"PROFIT","categoryTotal":false,"unit":"CURRENCY","industryCategoryId":"COMMERCE","industryTypeId":"FUNERAL_SERVICES"},{"id":"profit-COMMERCE-FURNITURE","parentId":"profit-COMMERCE","type":"PROFIT","categoryTotal":false,"unit":"CURRENCY","industryCategoryId":"COMMERCE","industryTypeId":"FURNITURE"},{"id":"profit-COMMERCE-MARKET","parentId":"profit-COMMERCE","type":"PROFIT","categoryTotal":false,"unit":"CURRENCY","industryCategoryId":"COMMERCE","industryTypeId":"MARKET"},{"id":"profit-COMMERCE-MOVIE","parentId":"profit-COMMERCE","type":"PROFIT","categoryTotal":false,"unit":"CURRENCY","industryCategoryId":"COMMERCE","industryTypeId":"MOVIE"},{"id":"profit-COMMERCE-RESTAURANT","parentId":"profit-COMMERCE","type":"PROFIT","categoryTotal":false,"unit":"CURRENCY","industryCategoryId":"COMMERCE","industryTypeId":"RESTAURANT"},{"id":"profit-COMMERCE-TOY","parentId":"profit-COMMERCE","type":"PROFIT","categoryTotal":false,"unit":"CURRENCY","industryCategoryId":"COMMERCE","industryTypeId":"TOY"},{"id":"profit-COMMERCE-COMPACT_DISC","parentId":"profit-COMMERCE","type":"PROFIT","categoryTotal":false,"unit":"CURRENCY","industryCategoryId":"COMMERCE","industryTypeId":"COMPACT_DISC"},{"id":"profit-COMMERCE-COMPUTER","parentId":"profit-COMMERCE","type":"PROFIT","categoryTotal":false,"unit":"CURRENCY","industryCategoryId":"COMMERCE","industryTypeId":"COMPUTER"},{"id":"profit-COMMERCE-GASOLINE","parentId":"profit-COMMERCE","type":"PROFIT","categoryTotal":false,"unit":"CURRENCY","industryCategoryId":"COMMERCE","industryTypeId":"GASOLINE"},{"id":"profit-COMMERCE-PHARMACEUTICAL","parentId":"profit-COMMERCE","type":"PROFIT","categoryTotal":false,"unit":"CURRENCY","industryCategoryId":"COMMERCE","industryTypeId":"PHARMACEUTICAL"},{"id":"profit-COMMERCE","parentId":"profit","type":"FOLDER","categoryTotal":false,"industryCategoryId":"COMMERCE","industryTypeId":null},{"id":"profit-COMMERCE-total","parentId":"profit-COMMERCE","type":"PROFIT","categoryTotal":true,"unit":"CURRENCY","industryCategoryId":"COMMERCE","industryTypeId":null},{"id":"profit-SERVICE-BANKING","parentId":"profit-SERVICE","type":"PROFIT","categoryTotal":false,"unit":"CURRENCY","industryCategoryId":"SERVICE","industryTypeId":"BANKING"},{"id":"profit-SERVICE-COMPUTER_SERVICES","parentId":"profit-SERVICE","type":"PROFIT","categoryTotal":false,"unit":"CURRENCY","industryCategoryId":"SERVICE","industryTypeId":"COMPUTER_SERVICES"},{"id":"profit-SERVICE-LEGAL_SERVICES","parentId":"profit-SERVICE","type":"PROFIT","categoryTotal":false,"unit":"CURRENCY","industryCategoryId":"SERVICE","industryTypeId":"LEGAL_SERVICES"},{"id":"profit-SERVICE-TELEVISION","parentId":"profit-SERVICE","type":"PROFIT","categoryTotal":false,"unit":"CURRENCY","industryCategoryId":"SERVICE","industryTypeId":"TELEVISION"},{"id":"profit-SERVICE","parentId":"profit","type":"FOLDER","categoryTotal":false,"industryCategoryId":"SERVICE","industryTypeId":null},{"id":"profit-SERVICE-total","parentId":"profit-SERVICE","type":"PROFIT","categoryTotal":true,"unit":"CURRENCY","industryCategoryId":"SERVICE","industryTypeId":null},{"id":"profit-REAL_ESTATE-OFFICE","parentId":"profit-REAL_ESTATE","type":"PROFIT","categoryTotal":false,"unit":"CURRENCY","industryCategoryId":"REAL_ESTATE","industryTypeId":"OFFICE"},{"id":"profit-REAL_ESTATE-HC_RESIDENTIAL","parentId":"profit-REAL_ESTATE","type":"PROFIT","categoryTotal":false,"unit":"CURRENCY","industryCategoryId":"REAL_ESTATE","industryTypeId":"HC_RESIDENTIAL"},{"id":"profit-REAL_ESTATE-LC_RESIDENTIAL","parentId":"profit-REAL_ESTATE","type":"PROFIT","categoryTotal":false,"unit":"CURRENCY","industryCategoryId":"REAL_ESTATE","industryTypeId":"LC_RESIDENTIAL"},{"id":"profit-REAL_ESTATE-MC_RESIDENTIAL","parentId":"profit-REAL_ESTATE","type":"PROFIT","categoryTotal":false,"unit":"CURRENCY","industryCategoryId":"REAL_ESTATE","industryTypeId":"MC_RESIDENTIAL"},{"id":"profit-REAL_ESTATE","parentId":"profit","type":"FOLDER","categoryTotal":false,"industryCategoryId":"REAL_ESTATE","industryTypeId":null},{"id":"profit-REAL_ESTATE-total","parentId":"profit-REAL_ESTATE","type":"PROFIT","categoryTotal":true,"unit":"CURRENCY","industryCategoryId":"REAL_ESTATE","industryTypeId":null},{"id":"profit-LOGISTICS-WAREHOUSE","parentId":"profit-LOGISTICS","type":"PROFIT","categoryTotal":false,"unit":"CURRENCY","industryCategoryId":"LOGISTICS","industryTypeId":"WAREHOUSE"},{"id":"profit-LOGISTICS","parentId":"profit","type":"FOLDER","categoryTotal":false,"industryCategoryId":"LOGISTICS","industryTypeId":null},{"id":"profit-LOGISTICS-total","parentId":"profit-LOGISTICS","type":"PROFIT","categoryTotal":true,"unit":"CURRENCY","industryCategoryId":"LOGISTICS","industryTypeId":null}],"resourceTypes":[{"id":"ADVERTISEMENTS","labelPlural":{"DE":"werbung","EN":"advertisements","ES":"anuncios","FR":"annonces","IT":"annunci","PT":"propagandas"},"unitId":"IMPRESSION","price":0.5},{"id":"APPLIANCE","labelPlural":{"DE":"haushaltsgeräte","EN":"appliances","ES":"accesorios","FR":"appareils électroménagers","IT":"elettrodomestici","PT":"eletrodomésticos"},"unitId":"ITEM","price":110},{"id":"AUTOMOBILE","labelPlural":{"DE":"automobile","EN":"automobiles","ES":"automóviles","FR":"automobiles","IT":"automobili","PT":"automóveis"},"unitId":"ITEM","price":7000},{"id":"BAR_SERVICE","labelPlural":{"DE":"bar-service","EN":"bar service","ES":"servicio de bar","FR":"service de bar","IT":"servizio bar","PT":"serviço de bar"},"unitId":"CUSTOMER","price":7},{"id":"BOOK","labelPlural":{"DE":"bücher","EN":"books","ES":"libros","FR":"livres","IT":"libri","PT":"livros"},"unitId":"ITEM","price":15},{"id":"CEMETERY_SERVICE","labelPlural":{"DE":"friedhofsdienste","EN":"cemetery services","ES":"servicios de cementerio","FR":"services de cimetière","IT":"servizi del cimitero","PT":"serviços de cemitério"},"unitId":"HOUR","price":0},{"id":"CHEMICAL","labelPlural":{"DE":"chemikalien","EN":"chemicals","ES":"productos químicos","FR":"produits chimiques","IT":"sostanze chimiche","PT":"produtos quimicos"},"unitId":"KILOGRAM","price":20},{"id":"CLOTHES","labelPlural":{"DE":"kleidung","EN":"clothing","ES":"ropa","FR":"vêtements","IT":"capi di abbigliamento","PT":"roupas"},"unitId":"ITEM","price":25},{"id":"COAL","labelPlural":{"DE":"kohle","EN":"coal","ES":"carbón","FR":"charbon","IT":"carbone","PT":"carvão"},"unitId":"KILOGRAM","price":1},{"id":"COMPACT_DISC","labelPlural":{"DE":"CDs","EN":"compact discs","ES":"discos compactos","FR":"disques compactes","IT":"compact disc","PT":"discos compactos"},"unitId":"ITEM","price":15},{"id":"COMPUTER","labelPlural":{"DE":"computers","EN":"computers","ES":"ordenadores","FR":"ordinateurs","IT":"computer","PT":"computadores"},"unitId":"ITEM","price":800},{"id":"COMPUTER_SERVICE","labelPlural":{"DE":"computer service","EN":"computer services","ES":"servicios informaticos","FR":"services informatiques","IT":"servizi informatici","PT":"serviços informáticos"},"unitId":"HOUR","price":200},{"id":"CONSTRUCTION","labelPlural":{"DE":"baukraft","EN":"construction force","ES":"fuerza de construcción","FR":"force de construction","IT":"forza di costruzione","PT":"força de construção"},"unitId":"TON","price":100},{"id":"CRIME","labelPlural":{"DE":"kriminalität","EN":"crime","ES":"crimen","FR":"criminalité","IT":"crimine","PT":"crime"},"unitId":"OCCURRENCE","price":0},{"id":"CRUDE_OIL","labelPlural":{"DE":"rohöl","EN":"crude oil","ES":"petróleo crudo","FR":"huile brute","IT":"olio crudo","PT":"óleo cru"},"unitId":"LITER","price":0.2},{"id":"EDUCATION_COLLEGE","labelPlural":{"DE":"universitäre ausbildung","EN":"college education","ES":"educación universitaria","FR":"éducation universitaire","IT":"istruzione universitaria","PT":"educação universitária"},"unitId":"HOUR","price":0},{"id":"EDUCATION_PRIMARY","labelPlural":{"DE":"grundschulbildung","EN":"primary education","ES":"educación primaria","FR":"enseignement primaire","IT":"istruzione elementare","PT":"educação primária"},"unitId":"HOUR","price":0},{"id":"ELECTRONIC_COMPONENT","labelPlural":{"DE":"elektronische bauteile","EN":"electronic components","ES":"componentes electrónicos","FR":"composants electroniques","IT":"componenti elettronici","PT":"componentes eletrônicos"},"unitId":"ITEM","price":50},{"id":"EXECUTIVE","labelPlural":{"DE":"exekutive arbeit","EN":"executive labor","ES":"trabajo ejecutivo","FR":"travail exécutif","IT":"lavoro esecutivo","PT":"trabalho executivo"},"unitId":"HOUR","price":20},{"id":"FABRIC","labelPlural":{"DE":"stoff","EN":"fabric","ES":"tela","FR":"en tissu","IT":"tessuto","PT":"tecido"},"unitId":"METER","price":6},{"id":"FILM","labelPlural":{"DE":"filme","EN":"films","ES":"películas","FR":"films","IT":"film","PT":"filmes"},"unitId":"LICENSE","price":500},{"id":"FRESH_FOOD","labelPlural":{"DE":"frisches essen","EN":"fresh food","ES":"comida fresca","FR":"nourriture fraîche","IT":"cibo fresco","PT":"comida fresca"},"unitId":"KILOGRAM","price":4},{"id":"FIRE_SERVICE","labelPlural":{"DE":"feuerwehrdienste","EN":"fire services","ES":"servicios de bomberos","FR":"services d'incendie","IT":"servizi antincendio","PT":"bombeiros"},"unitId":"HOUR","price":0},{"id":"FUNERAL_SERVICE","labelPlural":{"DE":"bestattungsinstitut","EN":"funeral services","ES":"servicios fúnebres","FR":"services funéraires","IT":"servizi funebri","PT":"serviços funerários"},"unitId":"CUSTOMER","price":5000},{"id":"FURNITURE","labelPlural":{"DE":"möbel","EN":"furniture","ES":"mueble","FR":"meubles","IT":"mobilia","PT":"mobília"},"unitId":"ITEM","price":100},{"id":"GARBAGE_SERVICE","labelPlural":{"DE":"mülldienstleistungen","EN":"garbage services","ES":"servicios de basura","FR":"services d'ordures","IT":"servizi di spazzatura","PT":"serviços de lixo"},"unitId":"KILOGRAM","price":0},{"id":"GASOLINE","labelPlural":{"DE":"benzin","EN":"gasoline","ES":"gasolina","FR":"de l'essence","IT":"gasolio","PT":"gasolina"},"unitId":"LITER","price":2},{"id":"LEGAL_SERVICE","labelPlural":{"DE":"rechtsberatung","EN":"legal services","ES":"servicios jurídicos","FR":"services juridiques","IT":"servizi legali","PT":"serviços legais"},"unitId":"HOUR","price":250},{"id":"LIQUOR","labelPlural":{"DE":"alkohol","EN":"liquor","ES":"espíritu","FR":"alcool","IT":"liquore","PT":"licor"},"unitId":"LITER","price":5},{"id":"MACHINERY","labelPlural":{"DE":"maschinen","EN":"machinery","ES":"maquinaria","FR":"machinerie","IT":"macchinario","PT":"máquinas"},"unitId":"ITEM","price":8000},{"id":"MEDICAL_SERVICE","labelPlural":{"DE":"medizinischer dienst","EN":"medical services","ES":"servicios médicos","FR":"services médicaux","IT":"servizi medici","PT":"serviços médicos"},"unitId":"HOUR","price":0},{"id":"METAL","labelPlural":{"DE":"metalle","EN":"metals","ES":"rieles","FR":"métaux","IT":"metalli","PT":"metais"},"unitId":"KILOGRAM","price":8},{"id":"MOVIE","labelPlural":{"DE":"filme","EN":"movies","ES":"películas","FR":"films","IT":"film","PT":"filmes"},"unitId":"ITEM","price":5},{"id":"MUSEUM_SERVICE","labelPlural":{"DE":"museumsdienstleistungen","EN":"museum services","ES":"servicios de museo","FR":"services du musée","IT":"servizi museali","PT":"serviços de museu"},"unitId":"HOUR","price":0},{"id":"ORE","labelPlural":{"DE":"erz","EN":"ore","ES":"mineral","FR":"minerai","IT":"minerale","PT":"minério"},"unitId":"KILOGRAM","price":1},{"id":"ORGANIC_MATERIAL","labelPlural":{"DE":"organisches material","EN":"organic material","ES":"material organico","FR":"matériau organique","IT":"materiale organico","PT":"material orgânico"},"unitId":"KILOGRAM","price":10},{"id":"PAPER","labelPlural":{"DE":"papier","EN":"paper","ES":"papel","FR":"papier","IT":"carta","PT":"papel"},"unitId":"KILOGRAM","price":15},{"id":"PHARMACEUTICAL","labelPlural":{"DE":"pharmazeutika","EN":"pharmaceuticals","ES":"productos farmacéuticos","FR":"médicaments","IT":"prodotti farmaceutici","PT":"fármacos"},"unitId":"KILOGRAM","price":40},{"id":"PLASTIC","labelPlural":{"DE":"kunststoff","EN":"plastic","ES":"plastico","FR":"plastique","IT":"plastica","PT":"plástico"},"unitId":"KILOGRAM","price":5},{"id":"POLICE_SERVICE","labelPlural":{"DE":"polizeidienste","EN":"police services","ES":"servicios policiales","FR":"services de police","IT":"servizi di polizia","PT":"serviços policiais"},"unitId":"HOUR","price":0},{"id":"POLLUTION","labelPlural":{"DE":"verschmutzung","EN":"pollution","ES":"contaminación","FR":"pollution","IT":"inquinamento","PT":"poluição"},"unitId":"KILOGRAM","price":8},{"id":"PRINTED_MATERIAL","labelPlural":{"DE":"gedrucktes material","EN":"printed material","ES":"material impreso","FR":"matériau imprimé","IT":"materiale stampato","PT":"material impresso"},"unitId":"KILOGRAM","price":25},{"id":"PRISON_SERVICE","labelPlural":{"DE":"gefängnisdienste","EN":"prison services","ES":"servicios penitenciarios","FR":"services pénitentiaires","IT":"servizi penitenziari","PT":"serviços prisionais"},"unitId":"KILOGRAM","price":0},{"id":"PROCESSED_FOOD","labelPlural":{"DE":"verarbeitete lebensmittel","EN":"processed food","ES":"alimentos procesados","FR":"aliments transformés","IT":"cibo trattato","PT":"comida processada"},"unitId":"ITEM","price":15},{"id":"PROFESSIONAL","labelPlural":{"DE":"berufliche arbeit","EN":"professional labor","ES":"labor profesional","FR":"travail professionnel","IT":"lavoro professionale","PT":"trabalho profissional"},"unitId":"HOUR","price":8},{"id":"RAW_CHEMICAL","labelPlural":{"DE":"rohchemikalien","EN":"raw chemicals","ES":"químicos crudos","FR":"produits chimiques bruts","IT":"prodotti chimici grezzi","PT":"produtos químicos em bruto"},"unitId":"KILOGRAM","price":1},{"id":"RECREATION_SERVICE","labelPlural":{"DE":"erholungsdienstleistungen","EN":"recreation services","ES":"servicios de recreación","FR":"services de loisirs","IT":"servizi ricreativi","PT":"serviços de recreação"},"unitId":"HOUR","price":200},{"id":"RESTAURANT_SERVICE","labelPlural":{"DE":"restaurant-service","EN":"restaurant service","ES":"servicio de restaurante","FR":"service de restauration","IT":"servizio ristorante","PT":"serviço de restaurante"},"unitId":"CUSTOMER","price":20},{"id":"SILICON","labelPlural":{"DE":"silizium","EN":"silicon","ES":"silicio","FR":"silicium","IT":"silicio","PT":"silício"},"unitId":"KILOGRAM","price":1},{"id":"STONE","labelPlural":{"DE":"stein","EN":"stone","ES":"piedra","FR":"pierre","IT":"pietra","PT":"pedra"},"unitId":"KILOGRAM","price":1},{"id":"TIMBER","labelPlural":{"DE":"bauholz","EN":"timber","ES":"madera","FR":"bois","IT":"legname","PT":"madeira"},"unitId":"KILOGRAM","price":2},{"id":"TOY","labelPlural":{"DE":"spielzeuge","EN":"toys","ES":"juguetes","FR":"jouets","IT":"giocattoli","PT":"brinquedos"},"unitId":"ITEM","price":32},{"id":"WORKER","labelPlural":{"DE":"körperliche arbeit","EN":"manual labor","ES":"trabajo físico","FR":"manual labor","IT":"lavoro fisico","PT":"trabalho braçal"},"unitId":"HOUR","price":2}],"resourceUnits":[{"id":"CUSTOMER","labelPlural":{"DE":"kunden","EN":"customers","ES":"clientes","FR":"clients","IT":"clienti","PT":"clientes"}},{"id":"HOUR","labelPlural":{"DE":"std","EN":"hours","ES":"horas","FR":"heures","IT":"ore","PT":"horas"}},{"id":"IMPRESSION","labelPlural":{"DE":"eindrücke","EN":"impressions","ES":"impresiones","FR":"impressions","IT":"impressioni","PT":"impressões"}},{"id":"ITEM","labelPlural":{"DE":"artikel","EN":"items","ES":"artículos","FR":"articles","IT":"elementi","PT":"unid"}},{"id":"KILOGRAM","labelPlural":{"DE":"kg","EN":"kg","ES":"kg","FR":"kg","IT":"kg","PT":"kg"}},{"id":"LICENSE","labelPlural":{"DE":"lizenzen","EN":"licenses","ES":"licencias","FR":"licences","IT":"licenze","PT":"licenças"}},{"id":"LITER","labelPlural":{"DE":"liters","EN":"liters","ES":"litros","FR":"litres","IT":"litri","PT":"litros"}},{"id":"METER","labelPlural":{"DE":"meters","EN":"meters","ES":"metros","FR":"mètres","IT":"metri","PT":"metros"}},{"id":"OCCURRENCE","labelPlural":{"DE":"auftreten","EN":"occurrence","ES":"ocurrencia","FR":"occurrence","IT":"evento","PT":"ocorrência"}},{"id":"TON","labelPlural":{"DE":"tonnen","EN":"tons","ES":"montones","FR":"tonnes","IT":"tonnellate","PT":"toneladas"}}],"seals":[{"id":"DIS","nameShort":"Dissidents","nameLong":"Dissidents","descriptions":[{"DE":"Dieser Siegelinhaber wurde von Markus Blomke, dem Gründer der IFEL, speziell eingeführt, um die politische Landschaft der Kolonien ins Gleichgewicht zu bringen. Der größte Teil der Technologie der Dissidenten ist funktionell und ideal für Anfänger","EN":"Introduced by Markus Blomke, founder of the IFEL, to balance the colonies' political landscape, most of the Dissident technology was designed to be ideal for beginners.","ES":"Esta tecnología fue introducida por Markus Blomke, fundador de la IFEL, para balancear el panorama político de las colonias. La mayoría de las tecnología Disidentes se hicieron con una alta funcionalidad e ideal para principiantes.","FR":"Cette corporation a été spécialement créée par le fondateur de la IFEL, Markus Blomke, pour équilibrer le paysage politique des colonies. La grande majorité des technologies Dissidentes a été conçue dans un souci de fonctionnalité et de simplicité pour les débutants.","IT":"Questo Seal fu introdotto da Markus Blomke, fondatore dell'IFEL, per bilanciare il panorama politico delle colonie. La maggior parte della tecnologia Dissidents mira alla elevata funzionalità ed è ideale per principianti.","PT":"Introduzido por Markus Blömke, fundador da IFEL, para equilibrar cenário político das colônias, a maior parte da tecnologia Dissident foi projetado para ser ideal para iniciantes."},{"DE":"Dissidents' Gebäude haben eine sehr niedrige Preise, aber die Qualität der Produktion ist gering und der Wirkungsgrad ist nicht die beste zur Verfügung. Dissidents hat die Exklusivität auf der Produktion von Likören, Spielzeug und Holz. Die beste Leistung ist in der Landwirtschaft, Software, Bars und Medien.","EN":"Dissidents' buildings sport very low prices, however the production quality is low and the efficiency level is not the best available. Dissidents have the exclusivity on the production of Liquors, Toys and Wood. Best performance is in farming, software, bars and media.","ES":"Edificios disidentes tienen precios muy bajos, sin embargo, la calidad de la producción es baja y el nivel de eficiencia no es la mejor disponible. Disidentes tienen la exclusividad en la producción de licores, Juguetes y madera. El mejor rendimiento consiste en el cultivo, software, bares y medios de comunicación.","FR":"Les bâtiments ont Dissidents des prix très bas, mais la qualité de la production est faible et le niveau d'efficacité est pas le meilleur disponible. Dissidents ont l'exclusivité sur la production de boissons, jouets et bois. La meilleure performance est dans l'agriculture, des logiciels, des bars et des médias.","IT":"Edifici dissidenti hanno prezzi molto bassi, tuttavia la qualità della produzione è bassa e il livello di efficienza non è il migliore disponibile. I dissidenti hanno l'esclusiva sulla produzione di liquori, giocattoli e Wood. Le migliori prestazioni sia in agricoltura, software, bar e mezzi di comunicazione.","PT":"Edifícios dos dissidentes têm preços muito baixos, no entanto, a qualidade da produção é baixa e o nível de eficiência não é a melhor disponível. Dissidentes têm a exclusividade na produção de licores, Brinquedos e Wood. Melhor desempenho é na agricultura, software, bares e mídia."}],"playable":true,"buildingIds":["dis.bank","dis.bar","dis.bm.industry","dis.book.store","dis.car.industry","dis.car.store","dis.chemical.industry","dis.chemical.industry.small","dis.clothes.industry","dis.clothes.industry.small","dis.clothes.store","dis.computing","dis.construction.industry","dis.elect.comp.industry","dis.elect.comp.industry.small","dis.farm","dis.farm.small","dis.food.proc","dis.food.proc.small","dis.food.store","dis.funeral","dis.furniture.industry","dis.furniture.store","dis.heavy.industry","dis.hha.industry","dis.hha.industry.small","dis.hha.store","dis.hi.res.a","dis.hi.res.b","dis.hi.res.c","dis.hi.res.d","dis.hospital","dis.hq","dis.legal.services","dis.liquor.industry","dis.lo.res.a","dis.lo.res.b","dis.lo.res.c","dis.lo.res.d","dis.lumber","dis.market.a","dis.market.b","dis.metal.industry","dis.metal.industry.small","dis.mi.res.a","dis.mi.res.b","dis.mi.res.c","dis.mi.res.d","dis.mi.res.e","dis.mi.res.f","dis.mine.coal","dis.mine.coal.small","dis.mine.ore","dis.mine.ore.small","dis.mine.chemical","dis.mine.chemical.small","dis.mine.silicon","dis.mine.silicon.small","dis.mine.stone","dis.mine.stone.small","dis.movie","dis.office.a","dis.office.b","dis.office.c","dis.park.small","dis.police","dis.restaurant.a","dis.restaurant.b","dis.school","dis.textile.industry","dis.textile.industry.small","dis.toy.industry","dis.toy.store","dis.tv.antenna","dis.tv.station","generic.college","generic.dump","generic.jail","generic.lo.cost.hi.res","generic.lo.cost.lo.res","generic.lo.cost.mi.res","generic.mausoleum.construction","generic.mausoleum.legend","generic.mausoleum.paradigm","generic.museum","generic.park.alien.a","generic.park.alien.b","generic.park.alien.c","generic.park.alien.d","generic.park.central","generic.park.medium","generic.park.small","generic.statue","generic.tennis","generic.tower","generic.warehouse.chemical","generic.warehouse.cold","generic.warehouse.cold.super","generic.warehouse.export","generic.warehouse.fabric","generic.warehouse.import","generic.warehouse.ore","generic.warehouse.univeral"],"pros":{"DE":"Sehr niedrige Preise. Niedrige Schadstoffniveaus. Kleine Designs, ideal für Unterschichtgebiete.","EN":"Very low prices. Low levels of pollution. Small designs ideal for low populated areas.","ES":"Muy bajos precios. Bajos niveles de contaminación. Pequeños diseños ideales para áreas de baja población.","FR":"Prix très faibles. Faibles niveaux de pollution. Constructions de faible hauteur, idéales dans les zones à faible densité.","IT":"Prezzi molto bassi. Bassi livelli di inquinamento. Architettura ridotta, ideale per aree poco popolate.","PT":"Preços muito baixos. Baixos níveis de poluição. Projetos pequenos, ideais para áreas pouco povoadas."},"cons":{"DE":"Niedrige Produktionsqualität. Niedrige Effizienz. Architektur gelegentlich unbeholfen.","EN":"Low quality of production. Low efficiency. Architecture is sometimes awkward.","ES":"Baja calidad de producción. Baja eficiencia. Algunas veces las Arquitectura son raras.","FR":"Qualité de production réduite. Efficacité limitée. Architecture parfois ingrate.","IT":"Bassa qualità produttiva. Bassa efficienza. L'architettura può sembrare strana.","PT":"Baixa qualidade de produção. Baixa eficiencia. A arquitetura às vezes é estranha."},"strengths":{"DE":"Landwirtschaft, Software, Bars und Medien","EN":"Farming, software, bars and media","ES":"Granja, software, bares y medios de comunicación","FR":"Fermes, SSII, bars et sociétés de communication","IT":"Fattorie, software, bar e media","PT":"Agricultura, software, bares e mídia"},"weaknesses":{"DE":"Wohnhäuser, Bergwerke, Metall und Schwerindustrie","EN":"Residentials buildings, mining, metalurgic and heavy industries","ES":"Residenciaes, minería, metalurgia y indrustrias pesadas","FR":"Immobilier résidentiel, mines, industries lourdes et métallurgie","IT":"Edifici residenziali, miniere, metallurgia e industrie pesanti","PT":"Edifícios residenciais, mineração, metalurgia e indústrias pesadas"}},{"id":"GEN","nameShort":"Public Domain","nameLong":"Public Domain","descriptions":[{"DE":"Technologie in der Public Domain.","EN":"Technology in the Public Domain.","ES":"La tecnología en el dominio público.","FR":"Technologie dans le domaine public.","IT":"La tecnologia nel pubblico dominio.","PT":"Tecnologia no Domínio Público."}],"playable":false,"buildingIds":["generic.college","generic.dump","generic.jail","generic.lo.cost.hi.res","generic.lo.cost.lo.res","generic.lo.cost.mi.res","generic.mausoleum.construction","generic.mausoleum.legend","generic.mausoleum.paradigm","generic.museum","generic.park.alien.a","generic.park.alien.b","generic.park.alien.c","generic.park.alien.d","generic.park.central","generic.park.medium","generic.park.small","generic.statue","generic.tennis","generic.tower","generic.warehouse.chemical","generic.warehouse.cold","generic.warehouse.cold.super","generic.warehouse.export","generic.warehouse.fabric","generic.warehouse.import","generic.warehouse.ore","generic.warehouse.univeral"],"pros":null,"cons":null,"strengths":null,"weaknesses":null},{"id":"MAGNA","nameShort":"Magna","nameLong":"Magna Corp","descriptions":[{"DE":"Die IFEL, die über die Überbevölkerung in den Kolonien besorgt ist, gab der Magna Corp. von der Erde ein Spezialsiegel.","EN":"The IFEL, concerned about overpopulation in the colonies, granted a Special Seal to Magna Corp from Earth.","ES":"La IFEL, preocupada por la superpoblación de las colonias, concederé una Marca Especial a la Corporación Magna desde la Tierra.","FR":"La IFEL a accordé une licence spéciale à Magna Corp depuis la Terre, qui s'inquiétait de la surpopulation dans les colonies.","IT":"L'IFEL, preoccupata per la sovrappopolazione, ha garantito un Seal speciale alla corporazione terrestre Magna.","PT":"O IFEL, preocupado com a superpopulação nas colônias, concedeu um Selo Especial à Magna Corp da Terra."},{"DE":"Magna hat sich auf sehr große Wohnstrukturen spezialisiert: Arkologien (massives Wohngebäude) und große Einkaufszentren.","EN":"Magna specialize in very large structures: Arcologies (massive residential buildings) and huge Commercial Centers. Movie Studios are the only Industry available. Seal can only be licensed to investors who achieved Paradigm level.","ES":"Magna se especializa en estructuras habitables muy grandes: Arcologías (enormes edificios residenciales) y grandes centros comerciales.","FR":"Magna est spécialise dans la construction de structures habitables d'envergure: Arcologies (bâtiments résidentiels massifs) et d'énormes centres commerciaux.","IT":"Magna è specializzata in strutture abitative estremamente grandi: Arcologie (edifici residenziali enormi) ed enormi centri commerciali.","PT":"Magna especializar-se em estruturas muito grandes: Arcologias (enormes edifícios residenciais) e grandes centros comerciais."}],"playable":true,"buildingIds":["magna.cloud.city","magna.construction","magna.heaven","magna.hive","magna.ivory.tower","magna.mayflower","magna.movie.studios","magna.movie.studios.construction","magna.octopus","magna.research.a","magna.research.b","magna.sky.dome","magna.solarium","magna.supermarket.a","magna.supermarket.b","magna.the.spring","magna.tulip","magna.whirlpool"],"pros":null,"cons":null,"strengths":null,"weaknesses":null},{"id":"MKO","nameShort":"Mariko","nameLong":"Mariko Enterprises","descriptions":[{"DE":"Mariko Enterprises bietet wettbewerbsfähige Lösungen, die auf den Kenntnissen basieren, die im letzten Jahrhundert von den Japanern entwickelt wurden.","EN":"Mariko Enterprises offers highly competitive solutions based on the knowledge developed by the Japanese in the last century.","ES":"Empresas Mariko oferta soluciones de elevada competitividad basadas en los conocimientos desarrollados por los japoneses en el siglo pasado.","FR":"Mariko Enterprises vous offre des solutions ultra compétitives héritées des connaissances développées par les japonais au siècle dernier.","IT":"Mariko Enterprises offre soluzioni estremamente competitive basate sulla conoscenza sviluppata dai Giapponesi nel secolo scorso.","PT":"A Mariko Enterprises oferece soluções altamente competitivas baseadas no conhecimento desenvolvido pelos japoneses no século passado."},{"DE":"Ihre Designs sind dafür bekannt, nur wenige Arbeiter zu benötigen.","EN":"Since Mariko Industries are highly automated, they need fewer workers and are very efficient. Their smaller structures are relatively low priced and guarantee less pollution. Plastic production and CDs are reserved to the Mariko Seal. Its strongest business areas are electronic components, lawyers, offices, household appliances and business machines.","ES":"Sus diseños son famosos debido al bajo número de trabajadores que se requieren.","FR":"Leurs schémas de production sont renommés pour les faibles taux d'effectif qu'ils requièrent.","IT":"Caratteristica fondamentale è il basso numero di lavoratori necessari.","PT":"Como as Indústrias Mariko são altamente automatizadas, elas precisam de menos trabalhadores e são muito eficientes. Suas estruturas menores têm preços relativamente baixos e garantem menos poluição. A produção de plásticos e CDs estão reservados ao Selo Mariko. Suas áreas de negócios mais fortes são componentes eletrônicos, advogados, escritórios, eletrodomésticos e máquinas comerciais."}],"playable":true,"buildingIds":["generic.college","generic.dump","generic.jail","generic.lo.cost.hi.res","generic.lo.cost.lo.res","generic.lo.cost.mi.res","generic.mausoleum.construction","generic.mausoleum.legend","generic.mausoleum.paradigm","generic.museum","generic.park.alien.a","generic.park.alien.b","generic.park.alien.c","generic.park.alien.d","generic.park.central","generic.park.medium","generic.park.small","generic.statue","generic.tennis","generic.tower","generic.warehouse.chemical","generic.warehouse.cold","generic.warehouse.cold.super","generic.warehouse.export","generic.warehouse.fabric","generic.warehouse.import","generic.warehouse.ore","generic.warehouse.univeral","mko.bm.industry","mko.car.industry","mko.car.store","mko.cd.industry","mko.cd.store","mko.chemical.industry","mko.chemical.industry.small","mko.clothes.industry","mko.clothes.industry.small","mko.clothes.store","mko.computer.store","mko.construction.industry","mko.elect.comp.industry","mko.elect.comp.industry.small","mko.farm","mko.farm.small","mko.food.proc","mko.food.proc.small","mko.food.store","mko.heavy.industry","mko.hha.industry","mko.hha.industry.small","mko.hha.store","mko.hi.res.a","mko.hi.res.b","mko.hi.res.c","mko.hospital","mko.hq","mko.lo.res.a","mko.lo.res.b","mko.lo.res.c","mko.lo.res.d","mko.lo.res.e","mko.market.a","mko.market.b","mko.market.c","mko.metal.industry","mko.metal.industry.small","mko.mi.res.a","mko.mi.res.b","mko.mi.res.c","mko.mi.res.d","mko.mi.res.e","mko.mi.res.f","mko.mi.res.g","mko.mine.coal","mko.mine.coal.small","mko.mine.chemical","mko.mine.chemical.small","mko.mine.ore","mko.mine.ore.small","mko.mine.silicon","mko.mine.silicon.small","mko.mine.stone","mko.mine.stone.small","mko.office.a","mko.office.b","mko.office.c","mko.office.d","mko.office.e","mko.office.f","mko.plastic.industry","mko.police","mko.school","mko.textile.industry","mko.textile.industry.small","mko.tv.station"],"pros":{"DE":"Niedrige Schadstoffwerte. Hoher Automatisierungsgrad der Industrie. Hohe Effizienz. Relativ niedrige Preise.","EN":"Low levels of pollution. Industies highly automated. High levels of efficency. Relatively low prices.","ES":"Bajos niveles de contaminación. Industrias altamente automatizadas. Altos niveles de eficiencia. Precios relativamente bajos.","FR":"Faibles niveaux de pollution. Industries largement automatisées. Niveaux d'efficacité élevés. Prix relativement bas.","IT":"Basso inquinamento. Industrie altamente automatizzate. Alti livelli di efficienza. Prezzi relativamente bassi.","PT":"Baixos níveis de poluição. Indústrias altamente automatizadas. Altos níveis de eficiência. Preços relativamente baixos."},"cons":{"DE":"Wenig resistent gegenüber Kriminalität und Umweltverschmutzung. Hohe Automatisierung kann zu Arbeitslosigkeit führen.","EN":"Low resistance to crime and pollution. High automation can increase unemployment.","ES":"Baja resistencia al Crimen y la contaminación. Elevada automatización puede incrementar el desempleo.","FR":"Peu d'emprise sur la criminalité et la pollution. Automatisation élevée génératrice de chômage.","IT":"Bassa resistenza al crimine e all'inquinamento. L'estesa automatizzazione può aumentare la disoccupazione.","PT":"Baixa resistência ao crime e poluição. Alta automação pode aumentar o desemprego."},"strengths":{"DE":"Elektronische Komponenten, Anwälte, Bürogebäude, Haushaltsgeräte und Ausrüstungsgüter","EN":"Electronic components, lawyers, office buildings, household appliances and business machines","ES":"Componentes electrónicos, abogados, oficinas, electrodomésticos e implementos de oficina","FR":"Composants électronique, avocats, bureaux, électroménager et biens d'équipement","IT":"Componenti elettronici, studi legali, uffici, elettrodomestici e macchine per ufficio","PT":"Componentes eletrônicos, advogados, prédios de escritórios, eletrodomésticos e máquinas comerciais"},"weaknesses":{"DE":"Lebensmittelherstellung, Wohnhäuser und Medien","EN":"Food processing, residentials buildings and media","ES":"Procesadoras de Alimentos, residenciales y medios de comunicación","FR":"Agro-alimentaire, immeubles résidentiels et sociétés de communication","IT":"Impianti alimentari, edifici residenziali e media","PT":"Processamento de alimentos, edifícios residenciais e mídia"}},{"id":"MOAB","nameShort":"Moab","nameLong":"The Moab","descriptions":[{"DE":"Die Moab sind ein religiöser Orden. Er wurde im letzten Jahrhundert von einem reichen deutschen Einwanderer in Texas gegründet. Moab ist ein Geisteszustand, der nur durch ein SM-Ritual erreicht werden kann. Nur die Mitglieder des Ordens sind eingeweiht.","EN":"The Moab is A religious order founded in Texas by a wealthy German immigrant. The Moab is a state of mind that can only be achieved by a sadomasochist ritual revealed only to those who embrace the cult.","ES":"El Moab es una orden religiosa. Fue fundado en el pasado siglo en Texas por un Inmigrante Alemán rico. El Moab es un estado mental que solo puede ser alcanzado por un ritual sado-masoquista revelado solo a aquellos que practican el culto.","FR":"Le Moab est un ordre religieux. Il fut fondée au siècle dernier, au Texas, par un riche immigrant allemand. Sa culture, fondée sur un rite sadomasochiste, est exclusivement transmise à ses adeptes.","IT":"Moab è un ordine religioso. Fu fondato nel secolo scorso in Texas da un ricco immigrato tedesco. Moab è uno stato mentale da raggiungere attraverso un rituale sado-masochistico svelato solo a chi diventa discepolo dell'ordine.","PT":"O Moab é uma ordem religiosa fundada no Texas por um rico imigrante alemão. O Moabe é um estado de espírito que só pode ser alcançado por um ritual sadomasoquista revelado apenas para aqueles que abraçam o culto."},{"DE":"Dank bürgerliche Gebäude Zentralisierung dieser Dichtung ist die beste Verbrechen und Feuer zu bekämpfen. Moab hat die Exklusivität der Öl- und Gasproduktionskette: Bohrinseln, Raffinerien und Tankstellen.","EN":"Thanks to civic building centralization, this seal is the best in fighting crime and fire. Moab has the exclusivity of the oil-gas production chain: oil rigs, refineries and gas stations.","ES":"Gracias a la centralización edificio civil, este sello es el mejor en la lucha contra la delincuencia y el fuego. Moab tiene la exclusividad de la cadena de producción de aceite y gas: plataformas petrolíferas, refinerías y estaciones de servicio.","FR":"Merci à la centralisation de la construction civile, ce sceau est le meilleur dans la lutte contre la criminalité et le feu. Moab a l'exclusivité de la chaîne de production de gaz de pétrole: plates-formes pétrolières, les raffineries et les stations-service.","IT":"Grazie al civico costruzione accentramento, questo sigillo è il migliore nella lotta contro il crimine e il fuoco. Moab ha l'esclusività della filiera olio-gas: piattaforme petrolifere, raffinerie e stazioni di servizio.","PT":"Graças a centralização edifício cívico, este selo é o melhor no combate ao crime e fogo. Moab tem a exclusividade da cadeia de produção de petróleo e gás: plataformas petrolíferas, refinarias e postos de gasolina."}],"playable":true,"buildingIds":["generic.college","generic.dump","generic.jail","generic.lo.cost.hi.res","generic.lo.cost.lo.res","generic.lo.cost.mi.res","generic.mausoleum.construction","generic.mausoleum.legend","generic.mausoleum.paradigm","generic.museum","generic.park.alien.a","generic.park.alien.b","generic.park.alien.c","generic.park.alien.d","generic.park.central","generic.park.medium","generic.park.small","generic.statue","generic.tennis","generic.tower","generic.warehouse.chemical","generic.warehouse.cold","generic.warehouse.cold.super","generic.warehouse.export","generic.warehouse.fabric","generic.warehouse.import","generic.warehouse.ore","generic.warehouse.univeral","moab.bar","moab.bm.industry","moab.car.industry","moab.car.store","moab.cathedral","moab.chemical.industry","moab.clothes.industry","moab.clothes.store","moab.computing","moab.construction.industry","moab.correctional","moab.correctional.tower","moab.elect.comp.industry","moab.farm","moab.food.proc","moab.food.store","moab.funeral","moab.gas.station","moab.heavy.industry","moab.hha.industry","moab.hha.store","moab.hi.res.a","moab.hi.res.b","moab.hi.res.c","moab.hi.res.d","moab.hq","moab.industry.tower","moab.legal.services","moab.lo.cost.mid.res","moab.lo.res.a","moab.lo.res.b","moab.lo.res.c","moab.lo.res.d","moab.market","moab.market.tower","moab.metal.industry","moab.mi.res.a","moab.mi.res.b","moab.mi.res.c","moab.mine.coal","moab.mine.chemical","moab.mine.ore","moab.mine.silicon","moab.mine.stone","moab.movie","moab.office.a","moab.office.b","moab.oil.rig","moab.refinery","moab.residential.tower","moab.restaurant","moab.textile.industry","moab.tv.station"],"pros":{"DE":"Stark in der Verbrechens- und Brandbekämpfung. Sehr effiziente Industrien. Moderate Preise.","EN":"Great crime and fire fighting. Very efficient industries. Moderate prices.","ES":"Bueno como Bomberos y Policías. Industrias muy eficientes. Precios Moderados.","FR":"Efficacité dans la lutte contre la criminalité et les incendies. Prix modérés.","IT":"Ottimo contro il crimine e gli incendi. Industrie molto efficienti. Prezzi moderati.","PT":"Bom crime e combate a incêndios. Indústrias muito eficientes. Preços moderados."},"cons":{"DE":"Dunkle, fast beängstigende Designs. Es gibt Leute, die nicht gerne in Moab-Industrien arbeiten. In ihren Wohnhäusern sollen seltsame Morde stattfinden.","EN":"Dark and sometimes frighting designs. Some people don't like to work in Moab industries. It has been told that strange murders occur in their residential buildings.","ES":"Diseños oscuros y algunas veces atemorizantes. A algunas personas no les gusta trabajar en las Industrias Moab. Se ha dicho que los asesinatos extraños ocurren en sus residenciales.","FR":"Architectures sombres et parfois effrayantes. Certaines personnes n'aiment pas travailler dans les industries Moab. On dit que des meurtres inexpliqués ont eu lieu dans leurs immeubles résidentiels.","IT":"Architettura cupa e talvolta intimidatoria. Non tutti vogliono lavorare nelle industrie Moab. Si mormora che strani omicidi avvengono nei loro edifici residenziali.","PT":"Desenhos escuros e às vezes assustadores. Algumas pessoas não gostam de trabalhar nas indústrias de Moabe. Foi dito que estranhos assassinatos ocorreram em seus prédios residenciais."},"strengths":{"DE":"Die besten Bergwerke und Chemikalien der Welt. Ober- und Unterschichtwohnhäuser","EN":"The best mining and chemicals in the world. High class and low class residentials","ES":"Las mejores minerías y químicos del mundo. Residenciales de Clase alta y baja","FR":"Les mines et les industries chimiques les plus performantes du monde. Immeubles résidentiels de classe supérieure et inférieure","IT":"Le migliori miniere e impianti chimici esistenti. Edifici residenziali di classe bassa e alta","PT":"A melhor mineração e produtos químicos do mundo. Residenciais de alta e baixa classe"},"weaknesses":{"DE":"Mittelschichtwohnhäuser und Medien. Landwirtschaft und Lebensmittelherstellung sind zweifelhaft","EN":"Middle class residentials and media. Farming and food processing methods are suspicious","ES":"Residenciales de Clase Media y medios de comunicación. Los métodos en las Granjas y Procesadoras de Alimentos son sospechosos","FR":"Immeubles résidentiels de classe moyenne et médias. Les techniques utilisées dans les fermes et les industries agro-alimentaires sont suspectes","IT":"Edifici residenziali di classe media. Metodi di coltivazione e trattamento di alimentari dubbi. Media","PT":"Residenciais e mídia de classe média. Métodos de cultivo e processamento de alimentos são suspeitos"}},{"id":"PGI","nameShort":"PGI","nameLong":"Pure Gaba Initiative","descriptions":[{"DE":"Die PGI, die von den reichsten Organisationen der Erde gegründet wurde, liefert einige der besten Technologien, die heute zur Verfügung stehen.","EN":"Founded by the wealthiest organizations in Europe, PGI provides some of the best technologies available today.","ES":"Fundada por la organización más adinerada de Europa, the PGI consta con algunas de las mejores tecnologías disponibles hoy en día.","FR":"Fondé par les entreprises les plus riches d'Europe, PGI met à votre disposition les technologies actuelles les plus évoluées.","IT":"Fondato dalle più ricche organizzazioni Europee, PGI fornisce le migliori tecnologie disponibili sul mercato.","PT":"Fundada pelas organizações mais ricas da Europa, a PGI fornece algumas das melhores tecnologias disponíveis hoje."},{"DE":"Diejenigen, die Effizienz und Qualität suchen, werden zufrieden sein. Ihre Designs sind allerdings manchmal sehr teuer.","EN":"PGI industries are efficient and showcase the best production quality available, but its facilities are very expensive. PGI is the only Seal allowed to produce Paper and Printing Materials.","ES":"Aquellos que buscan eficiencia y calida serón complacidos. Aunque sus diseños a veces son caros.","FR":"Les industries PGI sont efficaces et présentent la meilleure qualité de production disponible. Cependant, leur conception est coûteuse.","IT":"Eccellente per chi cerca efficienza e qualità. La loro architettura può però risultare molto costosa.","PT":"As indústrias PGI são eficientes e exibem a melhor qualidade de produção disponível, mas suas instalações são muito caras."}],"playable":true,"buildingIds":["generic.college","generic.dump","generic.jail","generic.lo.cost.hi.res","generic.lo.cost.lo.res","generic.lo.cost.mi.res","generic.mausoleum.construction","generic.mausoleum.legend","generic.mausoleum.paradigm","generic.museum","generic.park.alien.a","generic.park.alien.b","generic.park.alien.c","generic.park.alien.d","generic.park.central","generic.park.medium","generic.park.small","generic.statue","generic.tennis","generic.tower","generic.warehouse.chemical","generic.warehouse.cold","generic.warehouse.cold.super","generic.warehouse.export","generic.warehouse.fabric","generic.warehouse.import","generic.warehouse.ore","generic.warehouse.univeral","pgi.bar","pgi.bm.industry","pgi.car.industry","pgi.car.store","pgi.chemical.industry","pgi.chemical.industry.small","pgi.clothes.industry","pgi.clothes.industry.small","pgi.computing","pgi.const.industry","pgi.drug.store","pgi.elect.comp.industry","pgi.elect.comp.industry.small","pgi.farm","pgi.farm.small","pgi.fire","pgi.food.proc","pgi.food.proc.small","pgi.food.store","pgi.heavy.industry","pgi.hha.industry","pgi.hha.industry.small","pgi.hi.res.a","pgi.hi.res.b","pgi.hi.res.c","pgi.hi.res.d","pgi.hi.res.e","pgi.hi.res.f","pgi.hi.res.g","pgi.hi.res.h","pgi.hi.res.i","pgi.hi.res.j","pgi.hospital","pgi.hq","pgi.legal.services","pgi.lo.res.a","pgi.lo.res.b","pgi.lo.res.c","pgi.lo.res.d","pgi.lo.res.e","pgi.lo.res.f","pgi.market.a","pgi.market.b","pgi.market.c","pgi.metal.industry","pgi.metal.industry.small","pgi.mi.res.a","pgi.mi.res.b","pgi.mi.res.c","pgi.mi.res.d","pgi.mi.res.e","pgi.mine.coal","pgi.mine.coal.small","pgi.mine.chemical","pgi.mine.chemical.small","pgi.mine.ore","pgi.mine.ore.small","pgi.mine.silicon","pgi.mine.silicon.small","pgi.mine.stone","pgi.mine.stone.small","pgi.movie.a","pgi.movie.b","pgi.office.a","pgi.office.b","pgi.office.c","pgi.office.d","pgi.paper.industry","pgi.pharma.industry","pgi.police","pgi.printing.plant","pgi.restaurant","pgi.school","pgi.textile.industry","pgi.textile.industry.small","pgi.tv.station"],"pros":{"DE":"Sehr effiziente Industrie, mit der besten verfügbaren Produktionsqualität.","EN":"Very efficient industries, with the best production quality available.","ES":"Industrias muy eficientes, con las mejor producción de calidad disponible.","FR":"Industries extrêmement performantes, fournissant la meilleure qualité possible.","IT":"Industrie molto efficienti, con la migliore qualità di produzione disponibile.","PT":"Indústrias muito eficientes, com a melhor qualidade de produção disponível."},"cons":{"DE":"Hohe Preise. Manchmal sind Industrien zu groß.","EN":"High prices. Industries are too big sometimes.","ES":"Precios elevados. Las Industrias tienden a ser grandes.","FR":"Prix élevés. Les industries sont parfois trop importantes.","IT":"Prezzi elevati. Le industrie possono essere estremamente grosse.","PT":"Altos preços. Indústrias são muito grandes às vezes."},"strengths":{"DE":"Chemikalien, Bekleidung, Wohnhäuser, Geschäfte und andere Handelszentren","EN":"Chemicals, clothing, residential buildings, stores and other commerce centers","ES":"Químicos, ropas, residenciales, tiendas y otros centros comerciales","FR":"Industries chimiques, textiles, constructions immobilières, magasins et Centres de commerce","IT":"Chimica, vestiti, edifici residenziali, negozi e altri centri commerciali","PT":"Produtos químicos, roupas, edifícios residenciais, lojas e outros centros de comércio"},"weaknesses":{"DE":"Keine bekannt","EN":"None known","ES":"Ninguno conocido","FR":"Aucun connu","IT":"Nessuno conosciuto","PT":"Nenhum conhecido"}}]}